<?xml version="1.0" encoding="utf-8" ?>
<root>
  <contentType>basic page</contentType>
  <title>Enim praesent elementum facilisis leo vel fringilla est ullamcorper eget. </title>
  <sidebar>true</sidebar>
  <paragraphs>
    <paragraphType>media</paragraphType>
    <presentationType>small</presentationType>
    <mediaType>video</mediaType><video>https://www.youtube.com/watch?v=SB4xBBzNxVQ</video>
  </paragraphs>
  <paragraphs>
    <paragraphType>section break</paragraphType>
    <headline>Tellus mauris a diam maecenas sed enim ut sem. At lectus urna duis convallis convallis tellus id interdum velit. At elementum eu facilisis sed odio morbi quis. Habitant morbi tristique senectus et netus. </headline>
  </paragraphs>
  <paragraphs>
    <paragraphType>blockquote</paragraphType>
    <presentationType>full width</presentationType>
    <quote>Morbi tincidunt augue interdum velit euismod in. Enim eu turpis egestas pretium aenean pharetra magna ac placerat. </quote>
    <attribution> Aliqua Ut Elit Magna Ipsum </attribution>
  </paragraphs>
  <paragraphs>
    <paragraphType>basic text</paragraphType>

    <body>&quot;&lt;h3&gt;Lorem Ipsum&lt;/h3&gt;&lt;p&gt;&lt;strong&gt;Apollo 11&lt;/strong&gt; was the spaceflight that landed the first humans, Americans &lt;a href='http://en.wikipedia.org/wiki/Neil_Armstrong'&gt;Neil Armstrong&lt;/a&gt; and &lt;a href='http://en.wikipedia.org/wiki/Buzz_Aldrin'&gt;Buzz Aldrin&lt;/a&gt;, on the Moon on July 20th, 1969, at 20:18 UTC. Armstrong became &lt;em&gt;the first to step onto the lunar surface&lt;/em&gt; 6 hours later on July 21st at 02:56 UTC.&lt;/p&gt;&lt;p&gt;&lt;strong&gt;Apollo 11&lt;/strong&gt; was the spaceflight that landed the first humans, Americans &lt;a href='http://en.wikipedia.org/wiki/Neil_Armstrong'&gt;Neil Armstrong&lt;/a&gt; and &lt;a href='http://en.wikipedia.org/wiki/Buzz_Aldrin'&gt;Buzz Aldrin&lt;/a&gt;, on the Moon on July 20th, 1969, at 20:18 UTC. Armstrong became the first to step onto the lunar surface 6 hours later on July 21st at 02:56 UTC.&lt;/p&gt;&lt;h4&gt;Dolor Amit&lt;/h4&gt;&lt;ul&gt;&lt;li&gt;Lorem ipsum dolor amit&lt;/li&gt;&lt;li&gt;Consecutor verit&lt;/li&gt;&lt;li&gt;Item&lt;ul&gt;&lt;li&gt;nested item&lt;/li&gt;&lt;/ul&gt;&lt;/li&gt;&lt;/ul&gt;&lt;ol&gt;&lt;li&gt;Lorem ipsum dolor amit&lt;/li&gt;&lt;li&gt;Consecutor verit&lt;/li&gt;&lt;li&gt;Item&lt;ol&gt;&lt;li&gt;nested item&lt;/li&gt;&lt;/ol&gt;&lt;/li&gt;&lt;/ol&gt;&quot;</body>
  </paragraphs>
  <paragraphs>
    <paragraphType>media</paragraphType>
    <presentationType>large</presentationType>
    <mediaType>video</mediaType><video>https://www.youtube.com/watch?v=SB4xBBzNxVQ</video>
  </paragraphs>
  <paragraphs>
    <paragraphType>text list</paragraphType>
    <headline>Lorem Consectetur Lorem Elit </headline>
    <description>Donec ac odio tempor orci dapibus ultrices. Diam vulputate ut pharetra sit amet. </description>
    <items>
      <paragraphType>text list item</paragraphType><text>Vel quam elementum pulvinar etiam. </text>
    </items>
    <items>
      <paragraphType>text list item</paragraphType><text>Massa tincidunt nunc pulvinar sapien et ligula. </text>
    </items>
    <items>
      <paragraphType>text list item</paragraphType><text>Vestibulum morbi blandit cursus risus. </text>
    </items>
    <items>
      <paragraphType>text list item</paragraphType><text>Diam vulputate ut pharetra sit amet. </text>
    </items>
    <items>
      <paragraphType>text list item</paragraphType><text>Ac auctor augue mauris augue neque gravida in fermentum et. </text>
    </items>
    <items>
      <paragraphType>text list item</paragraphType><text>Faucibus scelerisque eleifend donec pretium. </text>
    </items>
    <items>
      <paragraphType>text list item</paragraphType><text>Ut etiam sit amet nisl purus. </text>
    </items>
    <items>
      <paragraphType>text list item</paragraphType><text>Facilisi cras fermentum odio eu feugiat pretium. </text>
    </items>
    <items>
      <paragraphType>text list item</paragraphType><text>Sapien et ligula ullamcorper malesuada proin libero nunc. </text>
    </items>
    <items>
      <paragraphType>text list item</paragraphType><text>Eget arcu dictum varius duis at consectetur lorem donec. </text>
    </items>
    <items>
      <paragraphType>text list item</paragraphType><text>Sit amet commodo nulla facilisi nullam vehicula. </text>
    </items>
    <items>
      <paragraphType>text list item</paragraphType><text>Dictum non consectetur a erat nam. </text>
    </items>
  </paragraphs>
  <paragraphs>
    <paragraphType>triptych panels</paragraphType>
    <panels>
      <paragraphType>icon triptych panel</paragraphType>
      <type>icon</type>
      <icon>
        <title>Elit Aliqua Eiusmod </title>
        <alt>Lorem Dolore Tempor </alt>
        <image>https://placekitten.com/100/100</image>
      </icon>
      <headline>Sit amet commodo nulla facilisi nullam vehicula. </headline>
      <description>Faucibus interdum posuere lorem ipsum. </description>
      <link><text>Lorem Sit </text>
      <path>#</path>
      </link>
    </panels>
    <panels>
      <paragraphType>button triptych panel</paragraphType>
      <type>button</type>
      <headline>Et malesuada fames ac turpis egestas. </headline>
      <description>Turpis egestas pretium aenean pharetra magna ac placerat vestibulum lectus. </description><button>
        <type>primary</type><text>Tempor Ipsum </text>
        <path>#</path>
      </button>
    </panels>
    <panels>
      <paragraphType>stat triptych panel</paragraphType>
      <type>stat</type>
      <statistic>341+</statistic>
      <headline>Facilisi cras fermentum odio eu feugiat pretium. </headline>
      <description>Viverra ipsum nunc aliquet bibendum enim facilisis gravida neque convallis. </description>
      <link><text>Et Sit </text>
      <path>#</path>
      </link>
    </panels>
  </paragraphs>
  <paragraphs>
    <paragraphType>media</paragraphType>
    <presentationType>large</presentationType>
    <mediaType>image</mediaType>
    <image>
      <alt>Vestibulum morbi blandit cursus risus. Bibendum neque egestas congue quisque egestas diam in arcu. </alt>
      <thumbnail>https://placekitten.com/180/120</thumbnail><small>https://placekitten.com/329/366</small>
      <medium>https://placekitten.com/681/739</medium>
      <large>https://placekitten.com/1100/1367</large>
    </image>
    <caption>Donec ac odio tempor orci dapibus ultrices. Donec ac odio tempor orci dapibus ultrices. </caption>
  </paragraphs>
  <paragraphs>
    <paragraphType>media</paragraphType>
    <presentationType>small</presentationType>
    <mediaType>image</mediaType>
    <image>
      <alt>At elementum eu facilisis sed odio morbi quis. Arcu ac tortor dignissim convallis aenean et tortor at. </alt>
      <thumbnail>https://placekitten.com/180/120</thumbnail><small>https://placekitten.com/367/332</small>
      <medium>https://placekitten.com/672/799</medium>
      <large>https://placekitten.com/1271/1105</large>
    </image>
    <caption>Dolor sit amet consectetur adipiscing elit pellentesque. Proin libero nunc consequat interdum varius sit amet mattis vulputate. </caption>
  </paragraphs>
  <paragraphs>
    <paragraphType>media</paragraphType>
    <presentationType>large</presentationType>
    <mediaType>image</mediaType>
    <image>
      <alt>Dignissim diam quis enim lobortis scelerisque fermentum. Dictum non consectetur a erat nam. </alt>
      <thumbnail>https://placekitten.com/180/120</thumbnail><small>https://placekitten.com/359/395</small>
      <medium>https://placekitten.com/716/616</medium>
      <large>https://placekitten.com/1170/1307</large>
    </image>
  </paragraphs>
  <paragraphs>
    <paragraphType>call to action</paragraphType><text>Egestas pretium aenean pharetra magna ac. </text><button>
      <type>primary</type><text>Amet Amet </text>
      <path>#</path>
    </button>
  </paragraphs>
  <paragraphs>
    <paragraphType>section break</paragraphType>
    <headline>Habitant morbi tristique senectus et netus. Nulla at volutpat diam ut venenatis. Posuere sollicitudin aliquam ultrices sagittis. Dictum non consectetur a erat nam. </headline>
  </paragraphs>
  <paragraphs>
    <paragraphType>blockquote</paragraphType>
    <presentationType>content width</presentationType>
    <quote>Donec ac odio tempor orci dapibus ultrices. Aliquet sagittis id consectetur purus ut faucibus pulvinar. </quote>
  </paragraphs>
  <paragraphs>
    <paragraphType>section break</paragraphType>
    <headline>Dictum non consectetur a erat nam. Tellus mauris a diam maecenas sed enim ut sem. Enim eu turpis egestas pretium aenean pharetra magna ac placerat. Dui accumsan sit amet nulla facilisi morbi tempus iaculis. </headline>
  </paragraphs>
  <paragraphs>
    <paragraphType>blockquote</paragraphType>
    <presentationType>full width</presentationType>
    <quote>Nisi lacus sed viverra tellus in hac habitasse platea dictumst. Augue ut lectus arcu bibendum at varius. </quote>
  </paragraphs>
  <paragraphs>
    <paragraphType>section break</paragraphType>
    <headline>Eget arcu dictum varius duis at consectetur lorem donec. Viverra ipsum nunc aliquet bibendum enim facilisis gravida neque convallis. Id diam maecenas ultricies mi eget mauris pharetra et. Malesuada bibendum arcu vitae elementum. </headline>
  </paragraphs>
  <paragraphs>
    <paragraphType>media</paragraphType>
    <presentationType>stripe</presentationType>
    <mediaType>image</mediaType>
    <image>
      <alt>Lectus urna duis convallis convallis tellus id interdum velit laoreet. At elementum eu facilisis sed odio morbi quis. </alt>
      <thumbnail>https://placekitten.com/180/120</thumbnail><small>https://placekitten.com/335/330</small>
      <medium>https://placekitten.com/666/749</medium>
      <large>https://placekitten.com/1203/1371</large>
    </image>
  </paragraphs>
  <paragraphs>
    <paragraphType>triptych panels</paragraphType>
    <panels>
      <paragraphType>news triptych panel</paragraphType>
      <type>news</type>
      <headline>Dolore Adipiscing Ut Labore </headline>
      <description>Enim praesent elementum facilisis leo vel fringilla est ullamcorper eget. Sapien nec sagittis aliquam malesuada. </description>
      <published>May 2, 2019</published>
      <featuredImage>
        <alt>Dui accumsan sit amet nulla facilisi morbi tempus iaculis. Dictum non consectetur a erat nam. </alt>
        <thumbnail>https://placekitten.com/180/120</thumbnail><small>https://placekitten.com/337/389</small>
        <medium>https://placekitten.com/697/706</medium>
        <large>https://placekitten.com/1163/1012</large>
      </featuredImage>
      <category><label>Consectetur Incididunt </label>
        <path>#</path>
      </category>
      <link>#</link>
    </panels>
    <panels>
      <paragraphType>news triptych panel</paragraphType>
      <type>news</type>
      <headline>Adipiscing Consectetur Et Dolore </headline>
      <description>Proin libero nunc consequat interdum varius sit amet mattis vulputate. Neque sodales ut etiam sit amet nisl. </description>
      <published>May 2, 2019</published>
      <featuredImage>
        <alt>Nulla at volutpat diam ut venenatis. Sapien et ligula ullamcorper malesuada proin libero nunc. </alt>
        <thumbnail>https://placekitten.com/180/120</thumbnail><small>https://placekitten.com/332/339</small>
        <medium>https://placekitten.com/666/734</medium>
        <large>https://placekitten.com/1187/1047</large>
      </featuredImage>
      <category><label>Adipiscing Elit </label>
        <path>#</path>
      </category>
      <link>#</link>
    </panels>
    <panels>
      <paragraphType>news triptych panel</paragraphType>
      <type>news</type>
      <headline>Sit Amet Labore Magna </headline>
      <description>Enim praesent elementum facilisis leo vel fringilla est ullamcorper eget. Sit amet commodo nulla facilisi nullam vehicula. </description>
      <published>May 2, 2019</published>
      <featuredImage>
        <alt>Eget arcu dictum varius duis at consectetur lorem donec. Vestibulum morbi blandit cursus risus. </alt>
        <thumbnail>https://placekitten.com/180/120</thumbnail><small>https://placekitten.com/391/370</small>
        <medium>https://placekitten.com/762/786</medium>
        <large>https://placekitten.com/1044/1365</large>
      </featuredImage>
      <category><label>Aliqua Consectetur </label>
        <path>#</path>
      </category>
      <link>#</link>
    </panels>
  </paragraphs>
  <paragraphs>
    <paragraphType>media</paragraphType>
    <presentationType>stripe</presentationType>
    <mediaType>video</mediaType><video>https://www.youtube.com/watch?v=SB4xBBzNxVQ</video>
    <caption>Enim praesent elementum facilisis leo vel fringilla est ullamcorper eget. Et malesuada fames ac turpis egestas. </caption>
  </paragraphs>
  <paragraphs>
    <paragraphType>photo gallery</paragraphType>
    <headline>Do Amet Incididunt Dolore </headline>
    <description>Sapien et ligula ullamcorper malesuada proin libero nunc. Lectus urna duis convallis convallis tellus id interdum velit laoreet. </description>
    <photos>
      <alt>Donec ac odio tempor orci dapibus ultrices. Id cursus metus aliquam eleifend mi. </alt>
      <thumbnail>https://placekitten.com/180/120</thumbnail><small>https://placekitten.com/319/350</small>
      <medium>https://placekitten.com/761/646</medium>
      <large>https://placekitten.com/1288/1005</large>
      <caption>Lectus urna duis convallis convallis tellus id interdum velit laoreet. </caption>
    </photos>
    <photos>
      <alt>Neque sodales ut etiam sit amet nisl. Faucibus scelerisque eleifend donec pretium. </alt>
      <thumbnail>https://placekitten.com/180/120</thumbnail><small>https://placekitten.com/342/305</small>
      <medium>https://placekitten.com/659/613</medium>
      <large>https://placekitten.com/1055/1026</large>
      <caption>Nulla porttitor massa id neque aliquam vestibulum morbi blandit. </caption>
    </photos>
    <photos>
      <alt>Viverra ipsum nunc aliquet bibendum enim facilisis gravida neque convallis. Id cursus metus aliquam eleifend mi. </alt>
      <thumbnail>https://placekitten.com/180/120</thumbnail><small>https://placekitten.com/391/394</small>
      <medium>https://placekitten.com/648/742</medium>
      <large>https://placekitten.com/1169/1149</large>
      <caption>Habitant morbi tristique senectus et netus. </caption>
    </photos>
    <photos>
      <alt>Urna porttitor rhoncus dolor purus non enim praesent elementum. Id diam maecenas ultricies mi eget mauris pharetra et. </alt>
      <thumbnail>https://placekitten.com/180/120</thumbnail><small>https://placekitten.com/323/384</small>
      <medium>https://placekitten.com/745/747</medium>
      <large>https://placekitten.com/1399/1004</large>
      <caption>Bibendum neque egestas congue quisque egestas diam in arcu. </caption>
    </photos>
    <photos>
      <alt>Dictum non consectetur a erat nam. Tellus mauris a diam maecenas sed enim. </alt>
      <thumbnail>https://placekitten.com/180/120</thumbnail><small>https://placekitten.com/304/336</small>
      <medium>https://placekitten.com/641/730</medium>
      <large>https://placekitten.com/1190/1167</large>
      <caption>Dolor sit amet consectetur adipiscing elit duis tristique sollicitudin. </caption>
    </photos>
    <photos>
      <alt>Tellus mauris a diam maecenas sed enim ut sem. Vitae tempus quam pellentesque nec nam aliquam sem. </alt>
      <thumbnail>https://placekitten.com/180/120</thumbnail><small>https://placekitten.com/361/371</small>
      <medium>https://placekitten.com/730/772</medium>
      <large>https://placekitten.com/1055/1042</large>
      <caption>Id cursus metus aliquam eleifend mi. </caption>
    </photos>
    <photos>
      <alt>Viverra ipsum nunc aliquet bibendum enim facilisis gravida neque convallis. Sapien et ligula ullamcorper malesuada proin libero nunc. </alt>
      <thumbnail>https://placekitten.com/180/120</thumbnail><small>https://placekitten.com/384/331</small>
      <medium>https://placekitten.com/609/683</medium>
      <large>https://placekitten.com/1199/1312</large>
      <caption>Dui accumsan sit amet nulla facilisi morbi tempus iaculis. </caption>
    </photos>
    <photos>
      <alt>Tempor orci dapibus ultrices in. Nisi lacus sed viverra tellus in hac habitasse platea dictumst. </alt>
      <thumbnail>https://placekitten.com/180/120</thumbnail><small>https://placekitten.com/388/381</small>
      <medium>https://placekitten.com/638/600</medium>
      <large>https://placekitten.com/1120/1045</large>
      <caption>Id diam maecenas ultricies mi eget mauris pharetra et. </caption>
    </photos>
    <photos>
      <alt>Massa tincidunt nunc pulvinar sapien et ligula. Dui accumsan sit amet nulla facilisi morbi tempus iaculis. </alt>
      <thumbnail>https://placekitten.com/180/120</thumbnail><small>https://placekitten.com/371/336</small>
      <medium>https://placekitten.com/656/776</medium>
      <large>https://placekitten.com/1316/1041</large>
      <caption>Arcu ac tortor dignissim convallis aenean et tortor at. </caption>
    </photos>
    <photos>
      <alt>At varius vel pharetra vel turpis nunc eget lorem dolor. Aliquet risus feugiat in ante metus dictum at. </alt>
      <thumbnail>https://placekitten.com/180/120</thumbnail><small>https://placekitten.com/368/321</small>
      <medium>https://placekitten.com/783/761</medium>
      <large>https://placekitten.com/1134/1065</large>
      <caption>Dolor sit amet consectetur adipiscing elit pellentesque. </caption>
    </photos>
    <photos>
      <alt>Magnis dis parturient montes nascetur ridiculus mus mauris vitae ultricies. Enim eu turpis egestas pretium aenean pharetra magna ac placerat. </alt>
      <thumbnail>https://placekitten.com/180/120</thumbnail><small>https://placekitten.com/329/318</small>
      <medium>https://placekitten.com/697/794</medium>
      <large>https://placekitten.com/1319/1268</large>
      <caption>Interdum velit euismod in pellentesque massa. </caption>
    </photos>
    <photos>
      <alt>Ut etiam sit amet nisl purus. Nulla at volutpat diam ut venenatis. </alt>
      <thumbnail>https://placekitten.com/180/120</thumbnail><small>https://placekitten.com/313/388</small>
      <medium>https://placekitten.com/648/671</medium>
      <large>https://placekitten.com/1363/1033</large>
      <caption>Turpis egestas pretium aenean pharetra magna ac placerat vestibulum lectus. </caption>
    </photos>
    <photos>
      <alt>Dui accumsan sit amet nulla facilisi morbi tempus iaculis. Leo in vitae turpis massa. </alt>
      <thumbnail>https://placekitten.com/180/120</thumbnail><small>https://placekitten.com/313/375</small>
      <medium>https://placekitten.com/716/649</medium>
      <large>https://placekitten.com/1048/1072</large>
      <caption>Dignissim diam quis enim lobortis scelerisque fermentum. </caption>
    </photos>
    <photos>
      <alt>Donec ac odio tempor orci dapibus ultrices. Fermentum iaculis eu non diam phasellus vestibulum lorem sed risus. </alt>
      <thumbnail>https://placekitten.com/180/120</thumbnail><small>https://placekitten.com/303/392</small>
      <medium>https://placekitten.com/739/744</medium>
      <large>https://placekitten.com/1347/1396</large>
      <caption>Dolor sit amet consectetur adipiscing elit duis tristique sollicitudin. </caption>
    </photos>
    <photos>
      <alt>Aliquet sagittis id consectetur purus ut faucibus pulvinar. Tortor id aliquet lectus proin. </alt>
      <thumbnail>https://placekitten.com/180/120</thumbnail><small>https://placekitten.com/394/310</small>
      <medium>https://placekitten.com/747/669</medium>
      <large>https://placekitten.com/1167/1187</large>
      <caption>Dignissim diam quis enim lobortis scelerisque fermentum. </caption>
    </photos>
    <photos>
      <alt>Praesent elementum facilisis leo vel fringilla est ullamcorper eget. Nulla facilisi morbi tempus iaculis urna id volutpat lacus laoreet. </alt>
      <thumbnail>https://placekitten.com/180/120</thumbnail><small>https://placekitten.com/352/302</small>
      <medium>https://placekitten.com/781/641</medium>
      <large>https://placekitten.com/1109/1020</large>
      <caption>Dictum at tempor commodo ullamcorper a lacus vestibulum sed arcu. </caption>
    </photos>
    <photos>
      <alt>Lectus urna duis convallis convallis tellus id interdum velit laoreet. Etiam dignissim diam quis enim. </alt>
      <thumbnail>https://placekitten.com/180/120</thumbnail><small>https://placekitten.com/343/384</small>
      <medium>https://placekitten.com/727/729</medium>
      <large>https://placekitten.com/1057/1228</large>
      <caption>Diam vulputate ut pharetra sit amet. </caption>
    </photos>
    <photos>
      <alt>Id cursus metus aliquam eleifend mi. At varius vel pharetra vel turpis nunc eget lorem dolor. </alt>
      <thumbnail>https://placekitten.com/180/120</thumbnail><small>https://placekitten.com/389/343</small>
      <medium>https://placekitten.com/699/655</medium>
      <large>https://placekitten.com/1122/1225</large>
      <caption>Viverra ipsum nunc aliquet bibendum enim facilisis gravida neque convallis. </caption>
    </photos>
    <photos>
      <alt>Viverra justo nec ultrices dui sapien eget mi proin sed. At varius vel pharetra vel turpis nunc eget lorem dolor. </alt>
      <thumbnail>https://placekitten.com/180/120</thumbnail><small>https://placekitten.com/352/362</small>
      <medium>https://placekitten.com/746/718</medium>
      <large>https://placekitten.com/1007/1292</large>
      <caption>Massa tincidunt nunc pulvinar sapien et ligula. </caption>
    </photos>
    <photos>
      <alt>Dui accumsan sit amet nulla facilisi morbi tempus iaculis. Dolor sit amet consectetur adipiscing elit duis tristique sollicitudin. </alt>
      <thumbnail>https://placekitten.com/180/120</thumbnail><small>https://placekitten.com/345/334</small>
      <medium>https://placekitten.com/769/702</medium>
      <large>https://placekitten.com/1057/1082</large>
      <caption>Nisi lacus sed viverra tellus in hac habitasse platea dictumst. </caption>
    </photos>
  </paragraphs>
  <paragraphs>
    <paragraphType>media</paragraphType>
    <presentationType>stripe</presentationType>
    <mediaType>image</mediaType>
    <image>
      <alt>Sapien et ligula ullamcorper malesuada proin libero nunc. Arcu ac tortor dignissim convallis aenean et tortor at. </alt>
      <thumbnail>https://placekitten.com/180/120</thumbnail><small>https://placekitten.com/386/392</small>
      <medium>https://placekitten.com/786/661</medium>
      <large>https://placekitten.com/1005/1288</large>
    </image>
    <caption>Aliquet sagittis id consectetur purus ut faucibus pulvinar. Proin libero nunc consequat interdum varius sit amet mattis vulputate. </caption>
  </paragraphs>
  <paragraphs>
    <paragraphType>course list</paragraphType>
    <headline>Ipsum Magna Eiusmod Incididunt </headline>
    <description>At elementum eu facilisis sed odio morbi quis. Lorem ipsum dolor sit amet, consectetur adipiscing elit, sed do eiusmod tempor incididunt ut labore et dolore magna aliqua. </description>
    <items>
      <paragraphType>course list item</paragraphType>
      <number>GLHLTH 123</number>
      <title>Amet Magna Eiusmod Ut </title>
    </items>
    <items>
      <paragraphType>course list item</paragraphType>
      <number>GLHLTH 123</number>
      <title>Dolore Eiusmod Incididunt Ipsum </title>
    </items>
    <items>
      <paragraphType>course list item</paragraphType>
      <number>GLHLTH 123</number>
      <title>Sed Magna Amet Dolore </title>
    </items>
    <items>
      <paragraphType>course list item</paragraphType>
      <number>GLHLTH 123</number>
      <title>Magna Consectetur Eiusmod Ipsum Labore </title>
    </items>
    <items>
      <paragraphType>course list item</paragraphType>
      <number>GLHLTH 123</number>
      <title>Sed Incididunt Adipiscing Amet </title>
    </items>
    <items>
      <paragraphType>course list item</paragraphType>
      <number>GLHLTH 123</number>
      <title>Sed Dolor Tempor Incididunt Dolor Lorem </title>
    </items>
    <items>
      <paragraphType>course list item</paragraphType>
      <number>GLHLTH 123</number>
      <title>Dolore Do Ut </title>
    </items>
    <items>
      <paragraphType>course list item</paragraphType>
      <number>GLHLTH 123</number>
      <title>Et Dolore Tempor Dolore Ut Incididunt </title>
    </items>
    <items>
      <paragraphType>course list item</paragraphType>
      <number>GLHLTH 123</number>
      <title>Incididunt Labore Et Consectetur Incididunt Sed </title>
    </items>
    <items>
      <paragraphType>course list item</paragraphType>
      <number>GLHLTH 123</number>
      <title>Tempor Ut Tempor Sed Magna </title>
    </items>
    <items>
      <paragraphType>course list item</paragraphType>
      <number>GLHLTH 123</number>
      <title>Et Dolore Labore Et </title>
    </items>
    <items>
      <paragraphType>course list item</paragraphType>
      <number>GLHLTH 123</number>
      <title>Labore Et Incididunt Do Adipiscing Aliqua </title>
    </items>
  </paragraphs>
  <paragraphs>
    <paragraphType>media</paragraphType>
    <presentationType>large</presentationType>
    <mediaType>video</mediaType><video>https://www.youtube.com/watch?v=SB4xBBzNxVQ</video>
    <caption>Dui accumsan sit amet nulla facilisi morbi tempus iaculis. Diam vulputate ut pharetra sit amet. </caption>
  </paragraphs>
  <paragraphs>
    <paragraphType>featured story</paragraphType>
    <presentationType>blue</presentationType>
    <headline>Amet Ipsum Et Dolore </headline>
    <description>Id cursus metus aliquam eleifend mi. Donec ac odio tempor orci dapibus ultrices. </description>
    <post>
      <headline>Et Consectetur Do Do </headline>
      <description>Tellus mauris a diam maecenas sed enim. Orci phasellus egestas tellus rutrum. </description>
      <published>May 2, 2019</published>
      <featuredImage>
        <alt>Ac auctor augue mauris augue neque gravida in fermentum et. Arcu dui vivamus arcu felis. </alt>
        <thumbnail>https://placekitten.com/180/120</thumbnail><small>https://placekitten.com/324/359</small>
        <medium>https://placekitten.com/772/605</medium>
        <large>https://placekitten.com/1268/1006</large>
      </featuredImage>
      <category><label>Eiusmod Sit </label>
        <path>#</path>
      </category>
      <link>#</link>
    </post>
  </paragraphs>
  <paragraphs>
    <paragraphType>media</paragraphType>
    <presentationType>small</presentationType>
    <mediaType>video</mediaType><video>https://www.youtube.com/watch?v=SB4xBBzNxVQ</video>
    <caption>Id cursus metus aliquam eleifend mi. Vitae tempus quam pellentesque nec nam aliquam sem. </caption>
  </paragraphs>
  <paragraphs>
    <paragraphType>call to action</paragraphType>
    <icon>
      <title>Magna Lorem Sit </title>
      <alt>Elit Ut Dolore </alt>
      <image>https://placekitten.com/100/100</image>
    </icon><text>Arcu dui vivamus arcu felis. </text><button>
      <type>primary</type><text>Et Labore </text>
      <path>#</path>
    </button>
  </paragraphs>
  <paragraphs>
    <paragraphType>basic text</paragraphType>

    <body>&quot;&lt;h3&gt;Lorem Ipsum&lt;/h3&gt;&lt;p&gt;&lt;strong&gt;Apollo 11&lt;/strong&gt; was the spaceflight that landed the first humans, Americans &lt;a href='http://en.wikipedia.org/wiki/Neil_Armstrong'&gt;Neil Armstrong&lt;/a&gt; and &lt;a href='http://en.wikipedia.org/wiki/Buzz_Aldrin'&gt;Buzz Aldrin&lt;/a&gt;, on the Moon on July 20th, 1969, at 20:18 UTC. Armstrong became &lt;em&gt;the first to step onto the lunar surface&lt;/em&gt; 6 hours later on July 21st at 02:56 UTC.&lt;/p&gt;&lt;p&gt;&lt;strong&gt;Apollo 11&lt;/strong&gt; was the spaceflight that landed the first humans, Americans &lt;a href='http://en.wikipedia.org/wiki/Neil_Armstrong'&gt;Neil Armstrong&lt;/a&gt; and &lt;a href='http://en.wikipedia.org/wiki/Buzz_Aldrin'&gt;Buzz Aldrin&lt;/a&gt;, on the Moon on July 20th, 1969, at 20:18 UTC. Armstrong became the first to step onto the lunar surface 6 hours later on July 21st at 02:56 UTC.&lt;/p&gt;&lt;h4&gt;Dolor Amit&lt;/h4&gt;&lt;ul&gt;&lt;li&gt;Lorem ipsum dolor amit&lt;/li&gt;&lt;li&gt;Consecutor verit&lt;/li&gt;&lt;li&gt;Item&lt;ul&gt;&lt;li&gt;nested item&lt;/li&gt;&lt;/ul&gt;&lt;/li&gt;&lt;/ul&gt;&lt;ol&gt;&lt;li&gt;Lorem ipsum dolor amit&lt;/li&gt;&lt;li&gt;Consecutor verit&lt;/li&gt;&lt;li&gt;Item&lt;ol&gt;&lt;li&gt;nested item&lt;/li&gt;&lt;/ol&gt;&lt;/li&gt;&lt;/ol&gt;&quot;</body>
  </paragraphs>
  <paragraphs>
    <paragraphType>media</paragraphType>
    <presentationType>stripe</presentationType>
    <mediaType>video</mediaType><video>https://www.youtube.com/watch?v=SB4xBBzNxVQ</video>
  </paragraphs>
  <paragraphs>
    <paragraphType>person list</paragraphType>
    <headline>Labore Consectetur Incididunt Dolore </headline>
    <description>Eget mauris pharetra et ultrices neque. Tellus mauris a diam maecenas sed enim. </description>
    <items>
      <paragraphType>person list item</paragraphType>
      <name>Sit Aliqua </name>
      <link>#</link>
    </items>
    <items>
      <paragraphType>person list item</paragraphType>
      <name>Sed Dolore </name>
      <link>#</link>
    </items>
    <items>
      <paragraphType>person list item</paragraphType>
      <name>Dolore Amet </name>
      <link>#</link>
    </items>
    <items>
      <paragraphType>person list item</paragraphType>
      <name>Amet Tempor </name>
      <link>#</link>
    </items>
    <items>
      <paragraphType>person list item</paragraphType>
      <name>Aliqua Amet </name>
      <link>#</link>
    </items>
    <items>
      <paragraphType>person list item</paragraphType>
      <name>Incididunt Dolore </name>
      <link>#</link>
    </items>
    <items>
      <paragraphType>person list item</paragraphType>
      <name>Et Dolor </name>
      <link>#</link>
    </items>
    <items>
      <paragraphType>person list item</paragraphType>
      <name>Adipiscing Aliqua </name>
      <link>#</link>
    </items>
    <items>
      <paragraphType>person list item</paragraphType>
      <name>Eiusmod Aliqua </name>
      <link>#</link>
    </items>
    <items>
      <paragraphType>person list item</paragraphType>
      <name>Tempor Aliqua </name>
      <link>#</link>
    </items>
    <items>
      <paragraphType>person list item</paragraphType>
      <name>Consectetur Adipiscing </name>
      <link>#</link>
    </items>
    <items>
      <paragraphType>person list item</paragraphType>
      <name>Tempor Dolore </name>
      <link>#</link>
    </items>
  </paragraphs>
  <paragraphs>
    <paragraphType>blockquote</paragraphType>
    <presentationType>content width</presentationType>
    <quote>At elementum eu facilisis sed odio morbi quis. Sapien et ligula ullamcorper malesuada proin libero nunc. </quote>
    <attribution> Tempor Sit Incididunt Ipsum Do </attribution>
  </paragraphs>
  <paragraphs>
    <paragraphType>section break</paragraphType>
    <headline>Tortor id aliquet lectus proin. Elementum curabitur vitae nunc sed. Et malesuada fames ac turpis egestas. Nulla porttitor massa id neque aliquam vestibulum morbi blandit. </headline>
  </paragraphs>
  <paragraphs>
    <paragraphType>featured story</paragraphType>
    <presentationType>regular</presentationType>
    <headline>Labore Et Adipiscing Lorem </headline>
    <description>Tortor condimentum lacinia quis vel eros donec ac odio. Adipiscing enim eu turpis egestas pretium aenean pharetra magna. </description>
    <post>
      <headline>Amet Adipiscing Sit Do </headline>
      <description>Neque sodales ut etiam sit amet nisl. Aliquet sagittis id consectetur purus ut faucibus pulvinar. </description>
      <published>May 2, 2019</published>
      <featuredImage>
        <alt>Bibendum neque egestas congue quisque egestas diam in arcu. Interdum velit euismod in pellentesque massa. </alt>
        <thumbnail>https://placekitten.com/180/120</thumbnail><small>https://placekitten.com/317/392</small>
        <medium>https://placekitten.com/614/683</medium>
        <large>https://placekitten.com/1196/1215</large>
      </featuredImage>
      <category><label>Ut Eiusmod </label>
        <path>#</path>
      </category>
      <link>#</link>
    </post>
  </paragraphs>
  <paragraphs>
    <paragraphType>media</paragraphType>
    <presentationType>small</presentationType>
    <mediaType>image</mediaType>
    <image>
      <alt>Potenti nullam ac tortor vitae purus. Massa tincidunt nunc pulvinar sapien et ligula. </alt>
      <thumbnail>https://placekitten.com/180/120</thumbnail><small>https://placekitten.com/373/399</small>
      <medium>https://placekitten.com/717/639</medium>
      <large>https://placekitten.com/1027/1391</large>
    </image>
  </paragraphs>
</root>