{
  "basicInfo": {
    "title": "Urna porttitor rhoncus dolor purus non enim praesent elementum.",
    "summary": "Facilisi cras fermentum odio eu feugiat pretium. Habitant morbi tristique senectus et netus. Malesuada bibendum arcu vitae elementum. Orci phasellus egestas tellus rutrum."
  },
  "classification": {
    "category": {
      "label": "Dolor Amet Sit",
      "path": "#"
    }
  },
  "featuredImage": {
    "alt": "Vel quam elementum pulvinar etiam. Diam vulputate ut pharetra sit amet.",
    "thumbnail": "https://placekitten.com/180/120",
    "small": "https://placekitten.com/370/389",
    "medium": "https://placekitten.com/729/758",
    "large": "https://placekitten.com/1111/1254",
    "caption": "Orci phasellus egestas tellus rutrum."
  },
  "dateTime": {
    "start": {
      "date": "January 1, 2020",
      "time": "9:00am"
    },
    "end": {
      "date": "January 1, 2020",
      "time": "10:00am"
    },
    "showEndDate": false
  },
  "venue": {
    "name": "Ahmadieh Family Auditorium,\n      Paul M. Gross Hall",
    "address": "123 Duke St\n      Durham, NC",
    "mapLink": "#",
    "parkingInfoLink": "#"
  },
  "contactPerson": {
    "name": "Lorem Ipsumson",
    "email": "duke.duke@duke.edu"
  },
  "buttons": [
    {
      "type": "primary",
      "text": "Ipsum Dolore",
      "path": "#"
    },
    {
      "type": "secondary",
      "text": "Amet Amet",
      "path": "#"
    }
  ],
  "body": "paragraphs",
  "api": {
    "importedBodyContent": "Morbi tincidunt augue interdum velit euismod in. Eget mauris pharetra et ultrices neque. Lorem ipsum dolor sit amet, consectetur adipiscing elit, sed do eiusmod tempor incididunt ut labore et dolore magna aliqua. Posuere sollicitudin aliquam ultrices sagittis. Massa ultricies mi quis hendrerit dolor. Habitant morbi tristique senectus et netus. Tellus mauris a diam maecenas sed enim. Id cursus metus aliquam eleifend mi. Neque sodales ut etiam sit amet nisl. At elementum eu facilisis sed odio morbi quis. Tellus mauris a diam maecenas sed enim. Aliquet risus feugiat in ante metus dictum at."
  }
}