{
  "type": "regular",
  "headline": "Lorem Do Ipsum Dolor",
  "description": "Vel quam elementum pulvinar etiam. Nulla porttitor massa id neque aliquam vestibulum morbi blandit.",
  "post": {
    "headline": "Dolore Dolore Lorem Incididunt",
    "description": "Tortor id aliquet lectus proin. Diam vulputate ut pharetra sit amet.",
    "published": "May 2, 2019",
    "featuredImage": {
      "alt": "Dui accumsan sit amet nulla facilisi morbi tempus iaculis. Proin libero nunc consequat interdum varius sit amet mattis vulputate.",
      "thumbnail": "https://placekitten.com/180/120",
      "small": "https://placekitten.com/326/341",
      "medium": "https://placekitten.com/664/700",
      "large": "https://placekitten.com/1072/1063"
    },
    "category": {
      "label": "Eiusmod Sit",
      "path": "#"
    },
    "link": "#"
  }
}