{
  "headline": "Magna Magna Consectetur Incididunt",
  "description": "Fermentum iaculis eu non diam phasellus vestibulum lorem sed risus. Potenti nullam ac tortor vitae purus.",
  "photos": [
    {
      "alt": "Enim praesent elementum facilisis leo vel fringilla est ullamcorper eget. Faucibus scelerisque eleifend donec pretium.",
      "thumbnail": "https://placekitten.com/180/120",
      "small": "https://placekitten.com/327/323",
      "medium": "https://placekitten.com/669/776",
      "large": "https://placekitten.com/1270/1177"
    },
    {
      "alt": "Fermentum iaculis eu non diam phasellus vestibulum lorem sed risus. Facilisi cras fermentum odio eu feugiat pretium.",
      "thumbnail": "https://placekitten.com/180/120",
      "small": "https://placekitten.com/379/365",
      "medium": "https://placekitten.com/636/667",
      "large": "https://placekitten.com/1132/1349"
    },
    {
      "alt": "At elementum eu facilisis sed odio morbi quis. Vitae tempus quam pellentesque nec nam aliquam sem.",
      "thumbnail": "https://placekitten.com/180/120",
      "small": "https://placekitten.com/305/321",
      "medium": "https://placekitten.com/781/672",
      "large": "https://placekitten.com/1267/1092"
    },
    {
      "alt": "At lectus urna duis convallis convallis tellus id interdum velit. Elementum pulvinar etiam non quam.",
      "thumbnail": "https://placekitten.com/180/120",
      "small": "https://placekitten.com/376/369",
      "medium": "https://placekitten.com/741/602",
      "large": "https://placekitten.com/1306/1214"
    },
    {
      "alt": "Arcu dui vivamus arcu felis bibendum ut tristique. Faucibus scelerisque eleifend donec pretium.",
      "thumbnail": "https://placekitten.com/180/120",
      "small": "https://placekitten.com/325/357",
      "medium": "https://placekitten.com/704/603",
      "large": "https://placekitten.com/1154/1093"
    },
    {
      "alt": "Interdum velit euismod in pellentesque massa. Adipiscing enim eu turpis egestas pretium aenean pharetra magna.",
      "thumbnail": "https://placekitten.com/180/120",
      "small": "https://placekitten.com/379/325",
      "medium": "https://placekitten.com/647/797",
      "large": "https://placekitten.com/1050/1113"
    },
    {
      "alt": "Leo in vitae turpis massa. Dictum non consectetur a erat nam.",
      "thumbnail": "https://placekitten.com/180/120",
      "small": "https://placekitten.com/367/328",
      "medium": "https://placekitten.com/717/785",
      "large": "https://placekitten.com/1233/1011"
    },
    {
      "alt": "Eget mauris pharetra et ultrices neque. Nisi lacus sed viverra tellus in hac habitasse platea dictumst.",
      "thumbnail": "https://placekitten.com/180/120",
      "small": "https://placekitten.com/394/346",
      "medium": "https://placekitten.com/716/636",
      "large": "https://placekitten.com/1399/1121"
    },
    {
      "alt": "Sapien et ligula ullamcorper malesuada proin libero nunc. Facilisi cras fermentum odio eu feugiat pretium.",
      "thumbnail": "https://placekitten.com/180/120",
      "small": "https://placekitten.com/344/349",
      "medium": "https://placekitten.com/629/611",
      "large": "https://placekitten.com/1185/1160"
    },
    {
      "alt": "Ultrices sagittis orci a scelerisque purus semper. Nisi lacus sed viverra tellus in hac habitasse platea dictumst.",
      "thumbnail": "https://placekitten.com/180/120",
      "small": "https://placekitten.com/355/332",
      "medium": "https://placekitten.com/633/762",
      "large": "https://placekitten.com/1315/1319"
    },
    {
      "alt": "Vestibulum morbi blandit cursus risus. Eu volutpat odio facilisis mauris sit amet.",
      "thumbnail": "https://placekitten.com/180/120",
      "small": "https://placekitten.com/320/397",
      "medium": "https://placekitten.com/740/743",
      "large": "https://placekitten.com/1115/1178"
    },
    {
      "alt": "Massa tincidunt nunc pulvinar sapien et ligula. Dignissim diam quis enim lobortis scelerisque fermentum.",
      "thumbnail": "https://placekitten.com/180/120",
      "small": "https://placekitten.com/351/380",
      "medium": "https://placekitten.com/785/678",
      "large": "https://placekitten.com/1147/1333"
    },
    {
      "alt": "Ac auctor augue mauris augue neque gravida in fermentum et. Nulla facilisi morbi tempus iaculis urna id volutpat lacus laoreet.",
      "thumbnail": "https://placekitten.com/180/120",
      "small": "https://placekitten.com/365/318",
      "medium": "https://placekitten.com/752/792",
      "large": "https://placekitten.com/1124/1033"
    },
    {
      "alt": "Praesent elementum facilisis leo vel fringilla est ullamcorper eget. Elementum curabitur vitae nunc sed.",
      "thumbnail": "https://placekitten.com/180/120",
      "small": "https://placekitten.com/366/334",
      "medium": "https://placekitten.com/741/699",
      "large": "https://placekitten.com/1227/1395"
    },
    {
      "alt": "Sapien nec sagittis aliquam malesuada. Habitant morbi tristique senectus et netus.",
      "thumbnail": "https://placekitten.com/180/120",
      "small": "https://placekitten.com/348/338",
      "medium": "https://placekitten.com/768/710",
      "large": "https://placekitten.com/1029/1373"
    },
    {
      "alt": "At lectus urna duis convallis convallis tellus id interdum velit. Et malesuada fames ac turpis egestas.",
      "thumbnail": "https://placekitten.com/180/120",
      "small": "https://placekitten.com/352/398",
      "medium": "https://placekitten.com/651/743",
      "large": "https://placekitten.com/1237/1043"
    },
    {
      "alt": "Viverra ipsum nunc aliquet bibendum enim facilisis gravida neque convallis. Elementum pulvinar etiam non quam.",
      "thumbnail": "https://placekitten.com/180/120",
      "small": "https://placekitten.com/368/349",
      "medium": "https://placekitten.com/721/719",
      "large": "https://placekitten.com/1040/1119"
    },
    {
      "alt": "Lorem ipsum dolor sit amet, consectetur adipiscing elit, sed do eiusmod tempor incididunt ut labore et dolore magna aliqua. Proin libero nunc consequat interdum varius sit amet mattis vulputate.",
      "thumbnail": "https://placekitten.com/180/120",
      "small": "https://placekitten.com/357/327",
      "medium": "https://placekitten.com/687/713",
      "large": "https://placekitten.com/1369/1353"
    },
    {
      "alt": "Fermentum iaculis eu non diam phasellus vestibulum lorem sed risus. Nulla facilisi morbi tempus iaculis urna id volutpat lacus laoreet.",
      "thumbnail": "https://placekitten.com/180/120",
      "small": "https://placekitten.com/319/355",
      "medium": "https://placekitten.com/663/644",
      "large": "https://placekitten.com/1138/1333"
    },
    {
      "alt": "Viverra ipsum nunc aliquet bibendum enim facilisis gravida neque convallis. Morbi tincidunt augue interdum velit euismod in.",
      "thumbnail": "https://placekitten.com/180/120",
      "small": "https://placekitten.com/337/313",
      "medium": "https://placekitten.com/655/756",
      "large": "https://placekitten.com/1299/1009"
    }
  ]
}