{
  "panels": [
    {
      "type": "news",
      "headline": "Ut Dolore Amet Ipsum",
      "description": "Enim eu turpis egestas pretium aenean pharetra magna ac placerat. Enim eu turpis egestas pretium aenean pharetra magna ac placerat.",
      "published": "May 2, 2019",
      "featuredImage": {
        "alt": "Praesent elementum facilisis leo vel fringilla est ullamcorper eget. Dolor sit amet consectetur adipiscing elit duis tristique sollicitudin.",
        "thumbnail": "https://placekitten.com/180/120",
        "small": "https://placekitten.com/376/385",
        "medium": "https://placekitten.com/626/720",
        "large": "https://placekitten.com/1152/1070"
      },
      "category": {
        "label": "Ut Ut",
        "path": "#"
      },
      "link": "#"
    },
    {
      "type": "news",
      "headline": "Ipsum Do Adipiscing Ut",
      "description": "Faucibus interdum posuere lorem ipsum. Arcu dui vivamus arcu felis.",
      "published": "May 2, 2019",
      "featuredImage": {
        "alt": "Vitae tempus quam pellentesque nec nam aliquam sem. Faucibus scelerisque eleifend donec pretium.",
        "thumbnail": "https://placekitten.com/180/120",
        "small": "https://placekitten.com/334/309",
        "medium": "https://placekitten.com/746/600",
        "large": "https://placekitten.com/1257/1087"
      },
      "category": {
        "label": "Elit Incididunt",
        "path": "#"
      },
      "link": "#"
    },
    {
      "type": "news",
      "headline": "Aliqua Dolore Do Et",
      "description": "Nulla porttitor massa id neque aliquam vestibulum morbi blandit. Nam aliquam sem et tortor.",
      "published": "May 2, 2019",
      "featuredImage": {
        "alt": "Orci phasellus egestas tellus rutrum. Tellus mauris a diam maecenas sed enim.",
        "thumbnail": "https://placekitten.com/180/120",
        "small": "https://placekitten.com/323/368",
        "medium": "https://placekitten.com/756/736",
        "large": "https://placekitten.com/1271/1163"
      },
      "category": {
        "label": "Sed Do",
        "path": "#"
      },
      "link": "#"
    }
  ]
}