<?xml version="1.0" encoding="utf-8" ?>
<root>
  <paragraphType>homepage hero panel</paragraphType>
  <headline>The Path to Health Equity</headline>
  <description>Elementum pulvinar etiam non quam. Posuere sollicitudin aliquam ultrices sagittis. </description><button>
    <type>primary</type><text>Sit Lorem </text>
    <path>#</path>
  </button>
  <alt>Tortor id aliquet lectus proin. Augue ut lectus arcu bibendum at varius. </alt>
  <thumbnail>https://placekitten.com/180/120</thumbnail><small>https://placekitten.com/375/308</small>
  <medium>https://placekitten.com/731/625</medium>
  <large>https://placekitten.com/1259/1335</large>
  <placement>left</placement>
</root>