<?xml version="1.0" encoding="utf-8" ?>
<root><label>Faculty Projects</label>
  <countries>
    <name>Equatorial Guinea</name><code>GQ</code>
    <path>#</path>
  </countries>
  <countries>
    <name>Tokelau</name><code>TK</code>
    <path>#</path>
  </countries>
  <countries>
    <name>Greenland</name><code>GL</code>
    <path>#</path>
  </countries>
  <countries>
    <name>Hong Kong</name><code>HK</code>
    <path>#</path>
  </countries>
  <countries>
    <name>Martinique</name><code>MQ</code>
    <path>#</path>
  </countries>
  <countries>
    <name>Cameroon</name><code>CM</code>
    <path>#</path>
  </countries>
  <countries>
    <name>Equatorial Guinea</name><code>GQ</code>
    <path>#</path>
  </countries>
  <countries>
    <name>Dominican Republic</name><code>DO</code>
    <path>#</path>
  </countries>
  <countries>
    <name>Tajikistan</name><code>TJ</code>
    <path>#</path>
  </countries>
  <countries>
    <name>Russia</name><code>RU</code>
    <path>#</path>
  </countries>
  <countries>
    <name>Thailand</name><code>TH</code>
    <path>#</path>
  </countries>
  <countries>
    <name>Mauritius</name><code>MU</code>
    <path>#</path>
  </countries>
  <countries>
    <name>Vietnam</name><code>VN</code>
    <path>#</path>
  </countries>
  <countries>
    <name>Liechtenstein</name><code>LI</code>
    <path>#</path>
  </countries>
  <countries>
    <name>Jordan</name><code>JO</code>
    <path>#</path>
  </countries>
</root>